groq_terminal_ai/__init__.py
groq_terminal_ai/cli.py
groq_terminal_ai/command_generator.py
groq_terminal_ai/config.py
groq_terminal_ai/models.py
groq_terminal_ai/utils.py
groq_terminal_ai-1.1.0.dist-info/METADATA
groq_terminal_ai-1.1.0.dist-info/WHEEL
groq_terminal_ai-1.1.0.dist-info/entry_points.txt
groq_terminal_ai-1.1.0.dist-info/top_level.txt
groq_terminal_ai-1.1.0.dist-info/RECORD
