Metadata-Version: 2.4
Name: groq-terminal-ai
Version: 1.1.0
Summary: groq-terminal-ai is a command line tool that uses AI to generate terminal commands
Requires-Dist: pyautogui
Requires-Dist: groq
